{
  "requesterUsername": "chauler",
  "requesterAvatarIconUri": {
    "$mid": 1,
    "path": "/chauler",
    "scheme": "https",
    "authority": "avatars.githubusercontent.com"
  },
  "responderUsername": "GitHub Copilot",
  "responderAvatarIconUri": {
    "id": "copilot"
  },
  "initialLocation": "panel",
  "welcomeMessage": [
    "Hi **@chauler**, how can I help you?"
  ],
  "requests": [
    {
      "message": {
        "parts": [
          {
            "range": {
              "start": 0,
              "endExclusive": 3179
            },
            "editorRange": {
              "startLineNumber": 1,
              "startColumn": 1,
              "endLineNumber": 102,
              "endColumn": 24
            },
            "text": "Context: You are an accessibility expert reviewing HTML for accessibility issues. Analyze the following code in the context of WCAG (Web Content Accessibility Guidelines) 2.2, listing any issues that may violate these guidelines. You will only be analyzing the HTML, ignoring any included or missing styles and scripts.\r\nCode: \r\n```<!DOCTYPE html>\r\n<html>\r\n<head>\r\n    <meta charset=\"UTF-8\">\r\n    <meta name=\"viewport\" content=\"width=device-width, initial-scale=1.0\">\r\n    <link rel=\"stylesheet\" href=\"styles.css\">\r\n    <title>Your Website</title>\r\n    <style>\r\n        body {\r\n            margin: 0;\r\n            padding: 0;\r\n            color: #333; /* Set default text color for better contrast */\r\n        }\r\n\r\n        h1 {\r\n            color: white;\r\n            background-color: #333; /* Updated background color for better contrast */\r\n            padding: 10px; /* Added padding for better visual appearance */\r\n        }\r\n\r\n        p {\r\n            color: #333; /* Set paragraph text color for better contrast */\r\n        }\r\n\r\n        button {\r\n            color: white;\r\n            background-color: #007BFF; /* Updated background color for better contrast */\r\n            padding: 8px 16px; /* Added padding for better visual appearance */\r\n            border: none;\r\n            cursor: pointer;\r\n        }\r\n\r\n        button:hover {\r\n            background-color: #0056b3; /* Darker color on hover for better contrast */\r\n        }\r\n\r\n        /* Add any additional styles as needed */\r\n    </style>\r\n</head>\r\n<body>\r\n\r\n    <header>\r\n        <nav>\r\n            <ul>\r\n                <li><a href=\"#home\">Home</a></li>\r\n                <li><a href=\"#about\">About</a></li>\r\n                <li><a href=\"#services\"></a></li>\r\n                <li><a href=\"#contact\">Contact</a></li>\r\n            </ul>\r\n        </nav>\r\n    </header>\r\n\r\n    <section id=\"home\" class=\"hero\">\r\n        <h1>Welcome to Your Website</h1>\r\n        <p>This is a simple and functional website template.</p>\r\n        <button onmousedown=\"playVideo()\">Play Video</button>\r\n    </section>\r\n\r\n    <section id=\"about\">\r\n        <h3>About Us</h3>\r\n        <p>Lorem ipsum dolor sit amet, consectetur adipiscing elit. ...</p>\r\n    </section>\r\n\r\n    <section id=\"services\">\r\n        <h2>Our Services</h2>\r\n        <ul>\r\n            <li>Service 1</li>\r\n            <li>Service 2</li>\r\n            <li>Service 3</li>\r\n        </ul>\r\n    </section>\r\n\r\n    <section id=\"contact\">\r\n        <h2>Contact Us</h2>\r\n        <form>\r\n            <label for=\"name\">Name:</label>\r\n            <input type=\"text\" id=\"name\" name=\"name\" required>\r\n            <br>\r\n            <label for=\"email\">Email:</label>\r\n            <input type=\"email\" id=\"email\" name=\"email\" required>\r\n            <br>\r\n            <input type=\"submit\" value=\"Submit\">\r\n        </form>\r\n    </section>\r\n\r\n    <meta http-equiv=\"refresh\" content=\"0\">\r\n\r\n    <footer>\r\n        <p>&copy; 2023 Your Website. All rights reserved.</p>\r\n    </footer>\r\n\r\n    <script src=\"script.js\"></script>\r\n</body>\r\n</html>```\r\nResponse format: \r\nSnippet with error: …\r\nLocation of error: …\r\nWCAG Guideline violated: …\r\nDetection Algorithm: …\r\nExplanation of Error: …",
            "kind": "text"
          }
        ],
        "text": "Context: You are an accessibility expert reviewing HTML for accessibility issues. Analyze the following code in the context of WCAG (Web Content Accessibility Guidelines) 2.2, listing any issues that may violate these guidelines. You will only be analyzing the HTML, ignoring any included or missing styles and scripts.\r\nCode: \r\n```<!DOCTYPE html>\r\n<html>\r\n<head>\r\n    <meta charset=\"UTF-8\">\r\n    <meta name=\"viewport\" content=\"width=device-width, initial-scale=1.0\">\r\n    <link rel=\"stylesheet\" href=\"styles.css\">\r\n    <title>Your Website</title>\r\n    <style>\r\n        body {\r\n            margin: 0;\r\n            padding: 0;\r\n            color: #333; /* Set default text color for better contrast */\r\n        }\r\n\r\n        h1 {\r\n            color: white;\r\n            background-color: #333; /* Updated background color for better contrast */\r\n            padding: 10px; /* Added padding for better visual appearance */\r\n        }\r\n\r\n        p {\r\n            color: #333; /* Set paragraph text color for better contrast */\r\n        }\r\n\r\n        button {\r\n            color: white;\r\n            background-color: #007BFF; /* Updated background color for better contrast */\r\n            padding: 8px 16px; /* Added padding for better visual appearance */\r\n            border: none;\r\n            cursor: pointer;\r\n        }\r\n\r\n        button:hover {\r\n            background-color: #0056b3; /* Darker color on hover for better contrast */\r\n        }\r\n\r\n        /* Add any additional styles as needed */\r\n    </style>\r\n</head>\r\n<body>\r\n\r\n    <header>\r\n        <nav>\r\n            <ul>\r\n                <li><a href=\"#home\">Home</a></li>\r\n                <li><a href=\"#about\">About</a></li>\r\n                <li><a href=\"#services\"></a></li>\r\n                <li><a href=\"#contact\">Contact</a></li>\r\n            </ul>\r\n        </nav>\r\n    </header>\r\n\r\n    <section id=\"home\" class=\"hero\">\r\n        <h1>Welcome to Your Website</h1>\r\n        <p>This is a simple and functional website template.</p>\r\n        <button onmousedown=\"playVideo()\">Play Video</button>\r\n    </section>\r\n\r\n    <section id=\"about\">\r\n        <h3>About Us</h3>\r\n        <p>Lorem ipsum dolor sit amet, consectetur adipiscing elit. ...</p>\r\n    </section>\r\n\r\n    <section id=\"services\">\r\n        <h2>Our Services</h2>\r\n        <ul>\r\n            <li>Service 1</li>\r\n            <li>Service 2</li>\r\n            <li>Service 3</li>\r\n        </ul>\r\n    </section>\r\n\r\n    <section id=\"contact\">\r\n        <h2>Contact Us</h2>\r\n        <form>\r\n            <label for=\"name\">Name:</label>\r\n            <input type=\"text\" id=\"name\" name=\"name\" required>\r\n            <br>\r\n            <label for=\"email\">Email:</label>\r\n            <input type=\"email\" id=\"email\" name=\"email\" required>\r\n            <br>\r\n            <input type=\"submit\" value=\"Submit\">\r\n        </form>\r\n    </section>\r\n\r\n    <meta http-equiv=\"refresh\" content=\"0\">\r\n\r\n    <footer>\r\n        <p>&copy; 2023 Your Website. All rights reserved.</p>\r\n    </footer>\r\n\r\n    <script src=\"script.js\"></script>\r\n</body>\r\n</html>```\r\nResponse format: \r\nSnippet with error: …\r\nLocation of error: …\r\nWCAG Guideline violated: …\r\nDetection Algorithm: …\r\nExplanation of Error: …"
      },
      "variableData": {
        "variables": []
      },
      "response": [
        {
          "value": "Snippet with error: `<li><a href=\"#services\"></a></li>`\nLocation of error: Inside the `<nav>` element in the `<header>`\nWCAG Guideline violated: 2.4.4 Link Purpose (In Context)\nDetection Algorithm: Check if all `<a>` tags have inner text or an `aria-label` attribute.\nExplanation of Error: The link does not have any text or an `aria-label` attribute, making it inaccessible for screen reader users as they won't know the purpose of the link.\n\nSnippet with error: `<button onmousedown=\"playVideo()\">Play Video</button>`\nLocation of error: Inside the `#home` section\nWCAG Guideline violated: 2.1.1 Keyboard\nDetection Algorithm: Check if interactive elements use device-independent event handlers.\nExplanation of Error: The button uses the `onmousedown` event, which is device-dependent and may not be accessible for keyboard users. It should use the `onclick` event instead.\n\nSnippet with error: `<meta http-equiv=\"refresh\" content=\"0\">`\nLocation of error: Inside the `<body>` element\nWCAG Guideline violated: 2.2.1 Timing Adjustable\nDetection Algorithm: Check if the page uses meta refresh tags.\nExplanation of Error: The meta refresh tag is used to refresh the page automatically, which can disorient users and doesn't allow them to control the timing of content updates.\n\nSnippet with error: `<input type=\"text\" id=\"name\" name=\"name\" required>`\nLocation of error: Inside the `#contact` section form\nWCAG Guideline violated: 3.3.2 Labels or Instructions\nDetection Algorithm: Check if form inputs have associated `<label>` elements.\nExplanation of Error: The input fields in the form are not programmatically associated with their labels. The `for` attribute of the `<label>` element should match the `id` of the associated `<input>` element.",
          "supportThemeIcons": false,
          "supportHtml": false
        }
      ],
      "result": {
        "timings": {
          "firstProgress": 2701,
          "totalElapsed": 18573
        },
        "metadata": {
          "responseId": "5038ec4d-0fea-44fe-aeb7-b215dfa6516e",
          "sessionId": "6f7d2090-825c-45e5-95b1-b146949e91fa"
        }
      },
      "followups": [
        {
          "kind": "reply",
          "agentId": "github.copilot.default",
          "message": "What is the purpose of the `aria-label` attribute in HTML?"
        }
      ],
      "isCanceled": false,
      "agent": {
        "b": {
          "extensionId": {
            "value": "GitHub.copilot-chat",
            "_lower": "github.copilot-chat"
          },
          "extensionPublisherDisplayName": "GitHub",
          "extensionPublisherId": "GitHub",
          "extensionDisplayName": "GitHub Copilot Chat",
          "id": "github.copilot.default",
          "description": "Ask Copilot or type / for commands",
          "metadata": {
            "fullName": "GitHub Copilot",
            "themeIcon": {
              "id": "copilot"
            },
            "hasFollowups": true,
            "helpTextPrefix": "You can ask me general programming questions, or chat with the following participants which have specialized expertise and can perform actions:",
            "helpTextVariablesPrefix": "You can also help me understand your question by using the following variables to give me extra context:",
            "helpTextPostfix": {
              "value": "To have a great conversation, ask me questions as if I was a real programmer:\n\n* **Show me the code** you want to talk about by having the files open and selecting the most important lines.\n* **Make refinements** by asking me follow-up questions, adding clarifications, providing errors, etc.\n* **Review my suggested code** and tell me about issues or improvements, so I can iterate on it.\n\nYou can also ask me questions about your editor selection by [starting an inline chat session](command:inlineChat.start).\n\nLearn more about [GitHub Copilot](https://docs.github.com/copilot/using-github-copilot/getting-started-with-github-copilot?tool=vscode&utm_source=editor&utm_medium=chat-panel&utm_campaign=2024q3-em-MSFT-getstarted) in [Visual Studio Code](https://code.visualstudio.com/docs/copilot/overview).",
              "isTrusted": {
                "enabledCommands": [
                  "inlineChat.start"
                ]
              },
              "supportThemeIcons": false,
              "supportHtml": false,
              "uris": {
                "command:inlineChat.start": {
                  "$mid": 1,
                  "path": "inlineChat.start",
                  "scheme": "command"
                },
                "https://docs.github.com/copilot/using-github-copilot/getting-started-with-github-copilot?tool=vscode&utm_source=editor&utm_medium=chat-panel&utm_campaign=2024q3-em-MSFT-getstarted": {
                  "$mid": 1,
                  "path": "/copilot/using-github-copilot/getting-started-with-github-copilot",
                  "scheme": "https",
                  "authority": "docs.github.com",
                  "query": "tool=vscode&utm_source=editor&utm_medium=chat-panel&utm_campaign=2024q3-em-MSFT-getstarted"
                },
                "https://code.visualstudio.com/docs/copilot/overview": {
                  "$mid": 1,
                  "path": "/docs/copilot/overview",
                  "scheme": "https",
                  "authority": "code.visualstudio.com"
                }
              }
            },
            "supportIssueReporting": false,
            "requester": {
              "name": "chauler",
              "icon": {
                "$mid": 1,
                "path": "/chauler",
                "scheme": "https",
                "authority": "avatars.githubusercontent.com"
              }
            }
          },
          "name": "GitHub Copilot",
          "isDefault": true,
          "locations": [
            "panel"
          ],
          "slashCommands": []
        },
        "d": {}
      },
      "contentReferences": [
        {
          "kind": "reference",
          "reference": {
            "uri": {
              "$mid": 1,
              "fsPath": "c:\\Users\\Alex\\Desktop\\A11y_AI\\RQ3-Results\\Project-10\\index.txt",
              "_sep": 1,
              "external": "file:///c%3A/Users/Alex/Desktop/A11y_AI/RQ3-Results/Project-10/index.txt",
              "path": "/c:/Users/Alex/Desktop/A11y_AI/RQ3-Results/Project-10/index.txt",
              "scheme": "file"
            },
            "range": {
              "startLineNumber": 1,
              "startColumn": 1,
              "endLineNumber": 102,
              "endColumn": 24
            }
          }
        }
      ]
    },
    {
      "message": {
        "parts": [
          {
            "range": {
              "start": 0,
              "endExclusive": 50
            },
            "editorRange": {
              "startLineNumber": 1,
              "startColumn": 1,
              "endLineNumber": 1,
              "endColumn": 51
            },
            "text": "Are there any more issues? List all that you find.",
            "kind": "text"
          }
        ],
        "text": "Are there any more issues? List all that you find."
      },
      "variableData": {
        "variables": []
      },
      "response": [
        {
          "value": "Snippet with error: `<h1>Welcome to Your Website</h1>`\nLocation of error: Inside the `#home` section\nWCAG Guideline violated: 1.4.3 Contrast (Minimum)\nDetection Algorithm: Check if the contrast ratio between text and background colors meets the minimum requirement.\nExplanation of Error: The contrast ratio between the white text and the `#333` background color may not meet the minimum requirement of 4.5:1 for normal text.\n\nSnippet with error: `<button onmousedown=\"playVideo()\">Play Video</button>`\nLocation of error: Inside the `#home` section\nWCAG Guideline violated: 4.1.2 Name, Role, Value\nDetection Algorithm: Check if all interactive components have accessible names.\nExplanation of Error: The button does not have an `aria-label` or `aria-labelledby` attribute, which may make it less accessible for screen reader users.\n\nSnippet with error: `<form>`\nLocation of error: Inside the `#contact` section\nWCAG Guideline violated: 3.3.1 Error Identification\nDetection Algorithm: Check if form validation errors are identified and described to the user in text.\nExplanation of Error: The form does not have any error identification mechanism in place. If a user makes an error, such as not filling out a required field, there is no text that describes the error to the user.\n\nSnippet with error: `<section id=\"home\" class=\"hero\">`\nLocation of error: Inside the `<body>` element\nWCAG Guideline violated: 1.3.1 Info and Relationships\nDetection Algorithm: Check if the document structure is conveyed through the use of proper markup.\nExplanation of Error: The sections of the page are not properly marked up with heading elements (`<h1>` to `<h6>`). This can make it difficult for screen reader users to understand the structure of the page. For example, the \"Welcome to Your Website\" text could be marked up as a `<h2>` element instead of a `<h1>`, as it is not the main title of the page.",
          "supportThemeIcons": false,
          "supportHtml": false
        }
      ],
      "result": {
        "timings": {
          "firstProgress": 1348,
          "totalElapsed": 14061
        },
        "metadata": {
          "responseId": "aa218494-8b11-4dcd-a7b5-38d70eb94c0c",
          "sessionId": "6f7d2090-825c-45e5-95b1-b146949e91fa"
        }
      },
      "followups": [
        {
          "kind": "reply",
          "agentId": "github.copilot.default",
          "message": "What are some best practices for improving accessibility in HTML?"
        }
      ],
      "isCanceled": false,
      "agent": {
        "b": {
          "extensionId": {
            "value": "GitHub.copilot-chat",
            "_lower": "github.copilot-chat"
          },
          "extensionPublisherDisplayName": "GitHub",
          "extensionPublisherId": "GitHub",
          "extensionDisplayName": "GitHub Copilot Chat",
          "id": "github.copilot.default",
          "description": "Ask Copilot or type / for commands",
          "metadata": {
            "fullName": "GitHub Copilot",
            "themeIcon": {
              "id": "copilot"
            },
            "hasFollowups": true,
            "helpTextPrefix": "You can ask me general programming questions, or chat with the following participants which have specialized expertise and can perform actions:",
            "helpTextVariablesPrefix": "You can also help me understand your question by using the following variables to give me extra context:",
            "helpTextPostfix": {
              "value": "To have a great conversation, ask me questions as if I was a real programmer:\n\n* **Show me the code** you want to talk about by having the files open and selecting the most important lines.\n* **Make refinements** by asking me follow-up questions, adding clarifications, providing errors, etc.\n* **Review my suggested code** and tell me about issues or improvements, so I can iterate on it.\n\nYou can also ask me questions about your editor selection by [starting an inline chat session](command:inlineChat.start).\n\nLearn more about [GitHub Copilot](https://docs.github.com/copilot/using-github-copilot/getting-started-with-github-copilot?tool=vscode&utm_source=editor&utm_medium=chat-panel&utm_campaign=2024q3-em-MSFT-getstarted) in [Visual Studio Code](https://code.visualstudio.com/docs/copilot/overview).",
              "isTrusted": {
                "enabledCommands": [
                  "inlineChat.start"
                ]
              },
              "supportThemeIcons": false,
              "supportHtml": false,
              "uris": {
                "command:inlineChat.start": {
                  "$mid": 1,
                  "path": "inlineChat.start",
                  "scheme": "command"
                },
                "https://docs.github.com/copilot/using-github-copilot/getting-started-with-github-copilot?tool=vscode&utm_source=editor&utm_medium=chat-panel&utm_campaign=2024q3-em-MSFT-getstarted": {
                  "$mid": 1,
                  "path": "/copilot/using-github-copilot/getting-started-with-github-copilot",
                  "scheme": "https",
                  "authority": "docs.github.com",
                  "query": "tool=vscode&utm_source=editor&utm_medium=chat-panel&utm_campaign=2024q3-em-MSFT-getstarted"
                },
                "https://code.visualstudio.com/docs/copilot/overview": {
                  "$mid": 1,
                  "path": "/docs/copilot/overview",
                  "scheme": "https",
                  "authority": "code.visualstudio.com"
                }
              }
            },
            "supportIssueReporting": false,
            "requester": {
              "name": "chauler",
              "icon": {
                "$mid": 1,
                "path": "/chauler",
                "scheme": "https",
                "authority": "avatars.githubusercontent.com"
              }
            }
          },
          "name": "GitHub Copilot",
          "isDefault": true,
          "locations": [
            "panel"
          ],
          "slashCommands": []
        },
        "d": {}
      },
      "contentReferences": [
        {
          "kind": "reference",
          "reference": {
            "uri": {
              "$mid": 1,
              "fsPath": "c:\\Users\\Alex\\Desktop\\A11y_AI\\RQ3-Results\\Project-10\\index.txt",
              "_sep": 1,
              "external": "file:///c%3A/Users/Alex/Desktop/A11y_AI/RQ3-Results/Project-10/index.txt",
              "path": "/c:/Users/Alex/Desktop/A11y_AI/RQ3-Results/Project-10/index.txt",
              "scheme": "file"
            },
            "range": {
              "startLineNumber": 1,
              "startColumn": 1,
              "endLineNumber": 102,
              "endColumn": 24
            }
          }
        }
      ]
    },
    {
      "message": {
        "parts": [
          {
            "range": {
              "start": 0,
              "endExclusive": 50
            },
            "editorRange": {
              "startLineNumber": 1,
              "startColumn": 1,
              "endLineNumber": 1,
              "endColumn": 51
            },
            "text": "Are there any more issues? List all that you find.",
            "kind": "text"
          }
        ],
        "text": "Are there any more issues? List all that you find."
      },
      "variableData": {
        "variables": []
      },
      "response": [
        {
          "value": "Snippet with error: `<h1>Welcome to Your Website</h1>`\nLocation of error: Inside the `#home` section\nWCAG Guideline violated: 1.4.3 Contrast (Minimum)\nDetection Algorithm: Check if the contrast ratio between text and background colors meets the minimum requirement.\nExplanation of Error: The contrast ratio between the white text and the `#333` background color may not meet the minimum requirement of 4.5:1 for normal text.\n\nSnippet with error: `<button onmousedown=\"playVideo()\">Play Video</button>`\nLocation of error: Inside the `#home` section\nWCAG Guideline violated: 4.1.2 Name, Role, Value\nDetection Algorithm: Check if all interactive components have accessible names.\nExplanation of Error: The button does not have an `aria-label` or `aria-labelledby` attribute, which may make it less accessible for screen reader users.\n\nSnippet with error: `<form>`\nLocation of error: Inside the `#contact` section\nWCAG Guideline violated: 3.3.1 Error Identification\nDetection Algorithm: Check if form validation errors are identified and described to the user in text.\nExplanation of Error: The form does not have any error identification mechanism in place. If a user makes an error, such as not filling out a required field, there is no text that describes the error to the user.\n\nSnippet with error: `<section id=\"home\" class=\"hero\">`\nLocation of error: Inside the `<body>` element\nWCAG Guideline violated: 1.3.1 Info and Relationships\nDetection Algorithm: Check if the document structure is conveyed through the use of proper markup.\nExplanation of Error: The sections of the page are not properly marked up with heading elements (`<h1>` to `<h6>`). This can make it difficult for screen reader users to understand the structure of the page. For example, the \"Welcome to Your Website\" text could be marked up as a `<h2>` element instead of a `<h1>`, as it is not the main title of the page.",
          "supportThemeIcons": false,
          "supportHtml": false
        }
      ],
      "result": {
        "timings": {
          "firstProgress": 1195,
          "totalElapsed": 13016
        },
        "metadata": {
          "responseId": "ac16847b-f742-4041-a841-ebdea31c1bb0",
          "sessionId": "6f7d2090-825c-45e5-95b1-b146949e91fa"
        }
      },
      "followups": [
        {
          "kind": "reply",
          "agentId": "github.copilot.default",
          "message": "What are some best practices for improving accessibility in HTML?"
        }
      ],
      "isCanceled": false,
      "agent": {
        "b": {
          "extensionId": {
            "value": "GitHub.copilot-chat",
            "_lower": "github.copilot-chat"
          },
          "extensionPublisherDisplayName": "GitHub",
          "extensionPublisherId": "GitHub",
          "extensionDisplayName": "GitHub Copilot Chat",
          "id": "github.copilot.default",
          "description": "Ask Copilot or type / for commands",
          "metadata": {
            "fullName": "GitHub Copilot",
            "themeIcon": {
              "id": "copilot"
            },
            "hasFollowups": true,
            "helpTextPrefix": "You can ask me general programming questions, or chat with the following participants which have specialized expertise and can perform actions:",
            "helpTextVariablesPrefix": "You can also help me understand your question by using the following variables to give me extra context:",
            "helpTextPostfix": {
              "value": "To have a great conversation, ask me questions as if I was a real programmer:\n\n* **Show me the code** you want to talk about by having the files open and selecting the most important lines.\n* **Make refinements** by asking me follow-up questions, adding clarifications, providing errors, etc.\n* **Review my suggested code** and tell me about issues or improvements, so I can iterate on it.\n\nYou can also ask me questions about your editor selection by [starting an inline chat session](command:inlineChat.start).\n\nLearn more about [GitHub Copilot](https://docs.github.com/copilot/using-github-copilot/getting-started-with-github-copilot?tool=vscode&utm_source=editor&utm_medium=chat-panel&utm_campaign=2024q3-em-MSFT-getstarted) in [Visual Studio Code](https://code.visualstudio.com/docs/copilot/overview).",
              "isTrusted": {
                "enabledCommands": [
                  "inlineChat.start"
                ]
              },
              "supportThemeIcons": false,
              "supportHtml": false,
              "uris": {
                "command:inlineChat.start": {
                  "$mid": 1,
                  "path": "inlineChat.start",
                  "scheme": "command"
                },
                "https://docs.github.com/copilot/using-github-copilot/getting-started-with-github-copilot?tool=vscode&utm_source=editor&utm_medium=chat-panel&utm_campaign=2024q3-em-MSFT-getstarted": {
                  "$mid": 1,
                  "path": "/copilot/using-github-copilot/getting-started-with-github-copilot",
                  "scheme": "https",
                  "authority": "docs.github.com",
                  "query": "tool=vscode&utm_source=editor&utm_medium=chat-panel&utm_campaign=2024q3-em-MSFT-getstarted"
                },
                "https://code.visualstudio.com/docs/copilot/overview": {
                  "$mid": 1,
                  "path": "/docs/copilot/overview",
                  "scheme": "https",
                  "authority": "code.visualstudio.com"
                }
              }
            },
            "supportIssueReporting": false,
            "requester": {
              "name": "chauler",
              "icon": {
                "$mid": 1,
                "path": "/chauler",
                "scheme": "https",
                "authority": "avatars.githubusercontent.com"
              }
            }
          },
          "name": "GitHub Copilot",
          "isDefault": true,
          "locations": [
            "panel"
          ],
          "slashCommands": []
        },
        "d": {}
      },
      "contentReferences": [
        {
          "kind": "reference",
          "reference": {
            "uri": {
              "$mid": 1,
              "fsPath": "c:\\Users\\Alex\\Desktop\\A11y_AI\\RQ3-Results\\Project-10\\index.txt",
              "_sep": 1,
              "external": "file:///c%3A/Users/Alex/Desktop/A11y_AI/RQ3-Results/Project-10/index.txt",
              "path": "/c:/Users/Alex/Desktop/A11y_AI/RQ3-Results/Project-10/index.txt",
              "scheme": "file"
            },
            "range": {
              "startLineNumber": 1,
              "startColumn": 1,
              "endLineNumber": 102,
              "endColumn": 24
            }
          }
        }
      ]
    }
  ]
}